README.md
setup.py
gym_utad/__init__.py
gym_utad.egg-info/PKG-INFO
gym_utad.egg-info/SOURCES.txt
gym_utad.egg-info/dependency_links.txt
gym_utad.egg-info/not-zip-safe
gym_utad.egg-info/requires.txt
gym_utad.egg-info/top_level.txt