Metadata-Version: 1.0
Name: gym-utad
Version: 1.0
Summary: Adaptation of OpenAI Gym envs
Home-page: https://github.com/u-tad-DMAA/gym-utad.git
Author: Pablo Ramos
Author-email: UNKNOWN
License: MIT
Platform: UNKNOWN
